ncloud_vserver/__init__.py
ncloud_vserver/api_client.py
ncloud_vserver/configuration.py
ncloud_vserver/rest.py
ncloud_vserver/api/__init__.py
ncloud_vserver/api/v2_api.py
ncloud_vserver/model/__init__.py
ncloud_vserver/model/access_control_group.py
ncloud_vserver/model/access_control_group_rule.py
ncloud_vserver/model/add_access_control_group_inbound_rule_request.py
ncloud_vserver/model/add_access_control_group_inbound_rule_response.py
ncloud_vserver/model/add_access_control_group_outbound_rule_request.py
ncloud_vserver/model/add_access_control_group_outbound_rule_response.py
ncloud_vserver/model/add_access_control_group_rule_parameter.py
ncloud_vserver/model/add_network_interface_access_control_group_request.py
ncloud_vserver/model/add_network_interface_access_control_group_response.py
ncloud_vserver/model/add_placement_group_server_instance_request.py
ncloud_vserver/model/add_placement_group_server_instance_response.py
ncloud_vserver/model/associate_public_ip_with_server_instance_request.py
ncloud_vserver/model/associate_public_ip_with_server_instance_response.py
ncloud_vserver/model/attach_block_storage_instance_request.py
ncloud_vserver/model/attach_block_storage_instance_response.py
ncloud_vserver/model/attach_network_interface_request.py
ncloud_vserver/model/attach_network_interface_response.py
ncloud_vserver/model/block_storage_instance.py
ncloud_vserver/model/block_storage_snapshot_instance.py
ncloud_vserver/model/change_block_storage_volume_size_request.py
ncloud_vserver/model/change_block_storage_volume_size_response.py
ncloud_vserver/model/change_server_instance_spec_request.py
ncloud_vserver/model/change_server_instance_spec_response.py
ncloud_vserver/model/common_code.py
ncloud_vserver/model/create_access_control_group_request.py
ncloud_vserver/model/create_access_control_group_response.py
ncloud_vserver/model/create_block_storage_instance_request.py
ncloud_vserver/model/create_block_storage_instance_response.py
ncloud_vserver-1.0.1.dist-info/LICENSE
ncloud_vserver-1.0.1.dist-info/METADATA
ncloud_vserver-1.0.1.dist-info/WHEEL
ncloud_vserver-1.0.1.dist-info/top_level.txt
ncloud_vserver-1.0.1.dist-info/RECORD
