Metadata-Version: 1.0
Name: ncloud-vserver
Version: 1.0.1
Summary: vserver
Home-page: UNKNOWN
Author: UNKNOWN
Author-email: UNKNOWN
License: UNKNOWN
Keywords: vserver
Platform: UNKNOWN
